OrthogonalBarcodes/OrthogonalBarcode.py
OrthogonalBarcodes-0.2.5.dist-info/LICENSE
OrthogonalBarcodes-0.2.5.dist-info/METADATA
OrthogonalBarcodes-0.2.5.dist-info/WHEEL
OrthogonalBarcodes-0.2.5.dist-info/top_level.txt
OrthogonalBarcodes-0.2.5.dist-info/RECORD
