Metadata-Version: 2.1
Name: OrthogonalBarcodes
Version: 0.2.5
Summary: A simple Python class for generating custom orthogonal DNA/RNA barcodes.
Home-page: https://github.com/kennypavan/OrthogonalBarcodes
Author: Kenny Pavan
Author-email: kennypavan@protonmail.com
Classifier: Programming Language :: Python :: 3
Classifier: License :: OSI Approved :: MIT License
Classifier: Operating System :: OS Independent
License-File: LICENSE
Requires-Dist: biopython (>=1.79)
Requires-Dist: numpy (>=1.23.1)
